coopr.core-2.0.4-py2.7-nspkg.pth
coopr/core/__init__.py
coopr/core/_command.py
coopr/core/_common.py
coopr/core/_config.py
coopr/core/_plugin.py
coopr/core/_task.py
coopr/core/plugin.py
coopr/core/tests/__init__.py
coopr/core/tests/test_task.py
coopr.core-2.0.4.dist-info/DESCRIPTION.rst
coopr.core-2.0.4.dist-info/METADATA
coopr.core-2.0.4.dist-info/metadata.json
coopr.core-2.0.4.dist-info/namespace_packages.txt
coopr.core-2.0.4.dist-info/RECORD
coopr.core-2.0.4.dist-info/top_level.txt
coopr.core-2.0.4.dist-info/WHEEL
